download_images_1/__init__.py
download_images_1/download_images.py
download_images_1-0.0.1.dist-info/METADATA
download_images_1-0.0.1.dist-info/WHEEL
download_images_1-0.0.1.dist-info/RECORD
